{
  "code": "COMP-PARITY-4",
  "description": "Loop create/resolve verbs in the UI. The attention queue already displays open loops but offers no create/resolve action — loop hygiene is terminal-only. Add create/resolve controls wired to the existing POST /api/vision/items/{id}/loops and .../loops/{loopId}/resolve endpoints the CLI already uses.",
  "status": "PLANNED",
  "phase": "COMP-PARITY: UI↔CLI Parity",
  "created": "2026-05-16",
  "updated": "2026-05-16",
  "complexity": "S",
  "position": 5,
  "parent": "COMP-PARITY",
  "group": "COMP-PARITY"
}
